gifCONVT_test/__init__.py
gifCONVT_test/gif_converter.py
gifCONVT_test-1.0.0.dist-info/LICENSE
gifCONVT_test-1.0.0.dist-info/METADATA
gifCONVT_test-1.0.0.dist-info/WHEEL
gifCONVT_test-1.0.0.dist-info/top_level.txt
gifCONVT_test-1.0.0.dist-info/RECORD
